LICENSE.md
README.md
waio/__init__.py
waio/bot.py
waio/client/__init__.py
waio/client/exceptions.py
waio/client/http.py
waio/dispatcher/__init__.py
waio/dispatcher/dispatcher.py
waio/dispatcher/event.py
waio/dispatcher/router.py
waio/factory/__init__.py
waio/factory/base.py
waio/factory/factory.py
waio/factory/models/__init__.py
waio/factory/models/basic.py
waio/factory/models/button.py
waio/factory/models/contact.py
waio/factory/models/document.py
waio/factory/models/image.py
waio/factory/models/list.py
waio/factory/models/main.py
waio/factory/models/response.py
waio/factory/models/text.py
waio/factory/models/webhook.py
waio/factory/schemas.py
waio/gupshup/__init__.py
waio/gupshup/api.py
waio/gupshup/form.py
waio/handlers/__init__.py
waio/handlers/abc.py
waio/handlers/base_handlers.py
waio/handlers/executor.py
waio/handlers/func_handler.py
waio/keyboard/__init__.py
waio/keyboard/list.py
waio/keyboard/reply.py
waio/labeler.py
waio/logs/__init__.py
waio/logs/log_level.py
waio/logs/logger.py
waio/middleware/__init__.py
waio/middleware/base.py
waio/middleware/type.py
waio/models/__init__.py
waio/models/audio.py
waio/models/enums.py
waio/models/file.py
waio/models/image.py
waio/models/sticker.py
waio/models/system/__init__.py
waio/models/system/handlers.py
waio/models/text.py
waio/models/video.py
waio/protocols/__init__.py
waio/protocols/bot.py
waio/rules/__init__.py
waio/rules/abc.py
waio/rules/default.py
waio/states/__init__.py
waio/states/context.py
waio/states/fsm.py
waio/storage/__init__.py
waio/storage/connector.py
waio/storage/redis.py
waio/types/__init__.py
waio/types/content_types.py
waio/types/message.py
waio/utils/__init__.py
waio/utils/callback/__init__.py
waio/utils/callback/base_callback.py
waio/utils/callback/base_filter.py
waio/utils/callback/callbacks.py
waio/utils/callback/filters.py
waio/utils/dicts.py
waio/utils/form_data.py
waio-0.2.0.0.dist-info/LICENSE.md
waio-0.2.0.0.dist-info/WHEEL
waio-0.2.0.0.dist-info/METADATA
waio-0.2.0.0.dist-info/RECORD
