Metadata-Version: 2.1
Name: waio
Version: 0.2.0.0
Summary: waio - is a pretty simple and fully asynchronous framework for WhatsApp Business API written in Python 3.7 with asyncio and aiohttp. Used API official Facebook partner - Gupshup.io
Home-page: https://github.com/dotX12/waio
License: MIT
Keywords: python,waio,whatsapp,asyncio,aiohttp,waba,whats,app,bot
Author: dotX12
Requires-Python: >=3.7,<4.0
Classifier: License :: OSI Approved :: MIT License
Classifier: Programming Language :: Python :: 3
Classifier: Programming Language :: Python :: 3.7
Classifier: Programming Language :: Python :: 3.8
Classifier: Programming Language :: Python :: 3.9
Classifier: Programming Language :: Python :: 3.10
Classifier: Programming Language :: Python :: 3.11
Requires-Dist: aiohttp (>=3.8.3,<4.0.0)
Requires-Dist: aioredis (==2.0.0)
Requires-Dist: dataclass-factory (>=2.11,<3.0)
Requires-Dist: loguru (>=0.5.3,<0.6.0)
Requires-Dist: magic-filter (>=1.0.9,<2.0.0)
Requires-Dist: ujson (==5.4.0)
Project-URL: Documentation, https://waio.readthedocs.io/
Project-URL: Repository, https://github.com/dotX12/waio
